tortto/VariableFunctions.py
tortto/__init__.py
tortto/serialization.py
tortto/tensor.py
tortto/test.py
tortto/xparray.py
tortto/autograd/__init__.py
tortto/autograd/function.py
tortto/autograd/grad_fcn.py
tortto/autograd/grad_fcn_config.yaml
tortto/autograd/grad_fcn_generator.py
tortto/autograd/grad_fcn_misc.py
tortto/autograd/grad_mode.py
tortto/autograd/grad_nn.py
tortto/autograd/helper.py
tortto/nn/__init__.py
tortto/nn/functional.py
tortto/nn/init.py
tortto/nn/parameter.py
tortto/nn/modules/__init__.py
tortto/nn/modules/activation.py
tortto/nn/modules/batchnorm.py
tortto/nn/modules/container.py
tortto/nn/modules/conv.py
tortto/nn/modules/dropout.py
tortto/nn/modules/linear.py
tortto/nn/modules/loss.py
tortto/nn/modules/module.py
tortto/nn/modules/normalization.py
tortto/nn/modules/pooling.py
tortto/nn/modules/sparse.py
tortto/nn/modules/transformer.py
tortto/nn/modules/utils.py
tortto/optim/__init__.py
tortto/optim/_functional.py
tortto/optim/adam.py
tortto/optim/adamw.py
tortto/optim/lr_scheduler.py
tortto/optim/optimizer.py
tortto/optim/sgd.py
tortto-1.3.4.dist-info/LICENSE
tortto-1.3.4.dist-info/METADATA
tortto-1.3.4.dist-info/WHEEL
tortto-1.3.4.dist-info/top_level.txt
tortto-1.3.4.dist-info/RECORD
