Metadata-Version: 2.1
Name: tortto
Version: 1.3.4
Summary: A PyTorch style machine learning framework written in NumPy with GPU acceleration from CuPy.
Home-page: https://github.com/samrere/pytortto
Author: Yu Hou
Author-email: hy1201750@gmail.com
Project-URL: Bug Tracker, https://github.com/samrere/pytortto/issues
Classifier: Programming Language :: Python :: 3
Classifier: License :: OSI Approved :: MIT License
Classifier: Operating System :: OS Independent
Classifier: Topic :: Scientific/Engineering :: Artificial Intelligence
Requires-Python: >=3.7
License-File: LICENSE
Requires-Dist: numpy >=1.24
